{
  "x-generator": "NSwag v14.1.0.0 (NJsonSchema v11.0.2.0 (Newtonsoft.Json v13.0.0.0))",
  "openapi": "3.0.0",
  "info": {
    "title": "WaffarXPartnerApi API",
    "version": "1.0.0"
  },
  "paths": {
    "/dashboard": {
      "get": {
        "operationId": "GetDashboard",
        "responses": {
          "200": {
            "description": ""
          }
        }
      }
    },
    "/api/StoreSettings/update": {
      "post": {
        "tags": [
          "StoreSettings"
        ],
        "operationId": "StoreSettings_UpdateStoreSettingList",
        "requestBody": {
          "x-name": "stores",
          "content": {
            "application/json": {
              "schema": {
                "type": "array",
                "items": {
                  "$ref": "#/components/schemas/StoreSettingRequestDto"
                }
              }
            }
          },
          "required": true,
          "x-position": 1
        },
        "responses": {
          "200": {
            "description": "",
            "content": {
              "application/octet-stream": {
                "schema": {
                  "type": "string",
                  "format": "binary"
                }
              }
            }
          }
        },
        "security": [
          {
            "JWT": []
          }
        ]
      }
    },
    "/api/StoreSettings/getwhitelistedstores": {
      "get": {
        "tags": [
          "StoreSettings"
        ],
        "operationId": "StoreSettings_GetWhiteListedStores",
        "responses": {
          "200": {
            "description": "",
            "content": {
              "application/octet-stream": {
                "schema": {
                  "type": "string",
                  "format": "binary"
                }
              }
            }
          }
        },
        "security": [
          {
            "JWT": []
          }
        ]
      }
    },
    "/api/StoreSettings/getallstore": {
      "get": {
        "tags": [
          "StoreSettings"
        ],
        "operationId": "StoreSettings_GetStoreLookUp",
        "responses": {
          "200": {
            "description": "",
            "content": {
              "application/octet-stream": {
                "schema": {
                  "type": "string",
                  "format": "binary"
                }
              }
            }
          }
        },
        "security": [
          {
            "JWT": []
          }
        ]
      }
    },
    "/api/Auth/login": {
      "post": {
        "tags": [
          "Auth"
        ],
        "operationId": "Auth_Login",
        "requestBody": {
          "x-name": "request",
          "content": {
            "application/json": {
              "schema": {
                "$ref": "#/components/schemas/LoginRequestDto"
              }
            }
          },
          "required": true,
          "x-position": 1
        },
        "responses": {
          "200": {
            "description": "",
            "content": {
              "application/octet-stream": {
                "schema": {
                  "type": "string",
                  "format": "binary"
                }
              }
            }
          }
        }
      }
    },
    "/api/Auth/register": {
      "post": {
        "tags": [
          "Auth"
        ],
        "operationId": "Auth_Register",
        "requestBody": {
          "x-name": "request",
          "content": {
            "application/json": {
              "schema": {
                "$ref": "#/components/schemas/RegisterRequestDto"
              }
            }
          },
          "required": true,
          "x-position": 1
        },
        "responses": {
          "200": {
            "description": "",
            "content": {
              "application/octet-stream": {
                "schema": {
                  "type": "string",
                  "format": "binary"
                }
              }
            }
          }
        }
      }
    },
    "/api/Auth/refreshtoken": {
      "post": {
        "tags": [
          "Auth"
        ],
        "operationId": "Auth_RefreshToken",
        "requestBody": {
          "x-name": "model",
          "content": {
            "application/json": {
              "schema": {
                "$ref": "#/components/schemas/TokenDto"
              }
            }
          },
          "required": true,
          "x-position": 1
        },
        "responses": {
          "200": {
            "description": "",
            "content": {
              "application/octet-stream": {
                "schema": {
                  "type": "string",
                  "format": "binary"
                }
              }
            }
          }
        }
      }
    },
    "/api/Auth/revoketoken": {
      "post": {
        "tags": [
          "Auth"
        ],
        "operationId": "Auth_RevokeToken",
        "requestBody": {
          "x-name": "model",
          "content": {
            "application/json": {
              "schema": {
                "$ref": "#/components/schemas/TokenDto"
              }
            }
          },
          "required": true,
          "x-position": 1
        },
        "responses": {
          "200": {
            "description": "",
            "content": {
              "application/octet-stream": {
                "schema": {
                  "type": "string",
                  "format": "binary"
                }
              }
            }
          }
        }
      }
    },
    "/api/Auth/validatetoken": {
      "post": {
        "tags": [
          "Auth"
        ],
        "operationId": "Auth_ValidateToken",
        "requestBody": {
          "x-name": "model",
          "content": {
            "application/json": {
              "schema": {
                "$ref": "#/components/schemas/TokenDto"
              }
            }
          },
          "required": true,
          "x-position": 1
        },
        "responses": {
          "200": {
            "description": "",
            "content": {
              "application/octet-stream": {
                "schema": {
                  "type": "string",
                  "format": "binary"
                }
              }
            }
          }
        }
      }
    }
  },
  "components": {
    "schemas": {
      "StoreSettingRequestDto": {
        "type": "object",
        "additionalProperties": false,
        "properties": {
          "storeId": {
            "type": "integer",
            "format": "int32"
          },
          "isFeatured": {
            "type": "boolean"
          },
          "rank": {
            "type": "integer",
            "format": "int32"
          }
        }
      },
      "LoginRequestDto": {
        "type": "object",
        "additionalProperties": false,
        "properties": {
          "username": {
            "type": "string",
            "nullable": true
          },
          "password": {
            "type": "string",
            "nullable": true
          }
        }
      },
      "RegisterRequestDto": {
        "type": "object",
        "additionalProperties": false,
        "properties": {
          "username": {
            "type": "string",
            "nullable": true
          },
          "email": {
            "type": "string",
            "nullable": true
          },
          "password": {
            "type": "string",
            "nullable": true
          },
          "firstName": {
            "type": "string",
            "nullable": true
          },
          "lastName": {
            "type": "string",
            "nullable": true
          },
          "clientApiId": {
            "type": "integer",
            "format": "int32"
          }
        }
      },
      "TokenDto": {
        "type": "object",
        "additionalProperties": false,
        "properties": {
          "token": {
            "type": "string"
          }
        }
      }
    },
    "securitySchemes": {
      "JWT": {
        "type": "apiKey",
        "description": "Type into the textbox: Bearer {your JWT token}.",
        "name": "Authorization",
        "in": "header"
      }
    }
  },
  "security": [
    {
      "JWT": []
    }
  ]
}